seaway/__init__.py
seaway/cli.py
seaway/core/__init__.py
seaway/core/app_project_init.py
seaway/core/base_project_init.py
seaway/core/module_init.py
seaway/core/module_project_init.py
seaway/template/.DS_Store
seaway/template/Android/.DS_Store
seaway/template/Android/AppProject/build.gradle
seaway/template/Android/AppProject/gradle.properties
seaway/template/Android/AppProject/settings.gradle
seaway/template/Android/ModuleProject/build.gradle
seaway/template/Android/ModuleProject/gradle.properties
seaway/utils/__init__.py
seaway/utils/cmd_utils.py
seaway/utils/file_utils.py
seaway/version/__init__.py
seaway/version/version_check.py
seaway-1.1.4.dist-info/METADATA
seaway-1.1.4.dist-info/WHEEL
seaway-1.1.4.dist-info/entry_points.txt
seaway-1.1.4.dist-info/top_level.txt
seaway-1.1.4.dist-info/zip-safe
seaway-1.1.4.dist-info/RECORD
