Metadata-Version: 2.1
Name: seaway
Version: 1.1.4
Summary: 客户端组件化CLI
Home-page: 
Author: wangshuwen
Author-email: 331835844@qq.com
License: MIT
Keywords: 组件化
Requires-Dist: requests
